collective.contentsections-2.0.0a4-py3.13-nspkg.pth
collective/contentsections/__init__.py
collective/contentsections/configure.zcml
collective/contentsections/indexers.py
collective/contentsections/indexers.zcml
collective/contentsections/interfaces.py
collective/contentsections/testing.py
collective/contentsections/vocabularies.py
collective/contentsections/vocabularies.zcml
collective/contentsections/behaviors/__init__.py
collective/contentsections/behaviors/configure.zcml
collective/contentsections/behaviors/leadicon.py
collective/contentsections/behaviors/namechooser.py
collective/contentsections/contents/__init__.py
collective/contentsections/contents/base.py
collective/contentsections/contents/configure.zcml
collective/contentsections/contents/contact/__init__.py
collective/contentsections/contents/contact/configure.zcml
collective/contentsections/contents/contact/content.py
collective/contentsections/contents/file/__init__.py
collective/contentsections/contents/file/configure.zcml
collective/contentsections/contents/image/__init__.py
collective/contentsections/contents/image/configure.zcml
collective/contentsections/contents/link/__init__.py
collective/contentsections/contents/link/configure.zcml
collective/contentsections/contents/link/views.py
collective/contentsections/contents/location/__init__.py
collective/contentsections/contents/location/configure.zcml
collective/contentsections/contents/location/content.py
collective/contentsections/distributions/sections/image.png
collective/contentsections/distributions/sections/profiles.json
collective/contentsections/distributions/sections/content/relations.json
collective/contentsections/distributions/sections/content/content/__metadata__.json
collective/contentsections/distributions/sections/content/content/081544c4943647f9b15b9e0905a9b54d/data.json
collective/contentsections/distributions/sections/content/content/0e43326bb88948c0b041a8133ce1e1fe/data.json
collective_contentsections-2.0.0a4.dist-info/licenses/LICENCE
collective_contentsections-2.0.0a4.dist-info/METADATA
collective_contentsections-2.0.0a4.dist-info/WHEEL
collective_contentsections-2.0.0a4.dist-info/entry_points.txt
collective_contentsections-2.0.0a4.dist-info/namespace_packages.txt
collective_contentsections-2.0.0a4.dist-info/top_level.txt
collective_contentsections-2.0.0a4.dist-info/RECORD
