Metadata-Version: 2.4
Name: collective.contentsections
Version: 2.0.0a4
Summary: A block approach for Plone 6 Classic
Home-page: https://github.com/collective/collective.contentsections
Author: Sébastien Verbois
Author-email: sebastien.verbois@gmail.com
License: GPL version 2
Project-URL: PyPI, https://pypi.python.org/pypi/collective.contentsections
Project-URL: Source, https://github.com/collective/collective.contentsections
Project-URL: Tracker, https://github.com/collective/collective.contentsections/issues
Keywords: Python Plone CMS
Classifier: Development Status :: 3 - Alpha
Classifier: Environment :: Web Environment
Classifier: Framework :: Plone
Classifier: Framework :: Plone :: Addon
Classifier: Framework :: Plone :: Distribution
Classifier: Framework :: Plone :: 6.1
Classifier: Programming Language :: Python
Classifier: Programming Language :: Python :: 3.10
Classifier: Programming Language :: Python :: 3.11
Classifier: Programming Language :: Python :: 3.12
Classifier: Programming Language :: Python :: 3.13
Classifier: Operating System :: OS Independent
Classifier: License :: OSI Approved :: GNU General Public License v2 (GPLv2)
Requires-Python: >=3.10
License-File: LICENCE
Requires-Dist: collective.geolocationbehavior>=1.7.2
Requires-Dist: collective.taxonomy>=3.1.5
Requires-Dist: collective.z3cform.datagridfield>=3.0.3
Requires-Dist: plone.api
Requires-Dist: plone.distribution
Requires-Dist: plone.formwidget.geolocation>=3.0.7
Requires-Dist: Products.CMFPlone
Requires-Dist: setuptools
Provides-Extra: test
Requires-Dist: plone.app.testing; extra == "test"
Requires-Dist: plone.app.contenttypes[test]; extra == "test"
Requires-Dist: Products.CMFPlacefulWorkflow; extra == "test"
Requires-Dist: pytest; extra == "test"
Requires-Dist: pytest-cov; extra == "test"
Requires-Dist: pytest-plone; extra == "test"
Requires-Dist: tox; extra == "test"
Dynamic: author
Dynamic: author-email
Dynamic: classifier
Dynamic: description
Dynamic: description-content-type
Dynamic: home-page
Dynamic: keywords
Dynamic: license
Dynamic: license-file
Dynamic: project-url
Dynamic: provides-extra
Dynamic: requires-dist
Dynamic: requires-python
Dynamic: summary
